capx_client/__init__.py
capx_client/api.py
capx_client/example.py
capx_client/solver.py
capx_client/utils.py
capx_client-1.0.1.dist-info/licenses/LICENSE
capx_client-1.0.1.dist-info/METADATA
capx_client-1.0.1.dist-info/WHEEL
capx_client-1.0.1.dist-info/top_level.txt
capx_client-1.0.1.dist-info/RECORD
