Metadata-Version: 2.4
Name: capx-client
Version: 1.0.1
Summary: capx client for solving reCAPTCHA challenges.
Author-email: Mahdi Marjani <mahdi.marjani.dev@gmail.com>
License-Expression: MIT
Project-URL: Homepage, https://github.com/mahdi-marjani/capx-client
Project-URL: Documentation, https://github.com/mahdi-marjani/capx-client
Project-URL: Repository, https://github.com/mahdi-marjani/capx-client.git
Project-URL: Issues, https://github.com/mahdi-marjani/capx-client/issues
Requires-Python: >=3.8
License-File: LICENSE
Requires-Dist: numpy>=2.2.6
Requires-Dist: Pillow>=12.1.0
Requires-Dist: Requests>=2.32.5
Requires-Dist: selenium>=4.39.0
Requires-Dist: webdriver_manager>=4.0.2
Dynamic: license-file
